[{"id":1,"name":"Riane Okeshott","description":"vulputate ut ultrices vel augue vestibulum ante ipsum primis in faucibus orci luctus et ultrices posuere","createdAt":"2022-01-28 08:23:29","updatedAt":"2021-08-16 19:31:26"},
{"id":2,"name":"Moyna Bartoszinski","description":"aliquet at feugiat non pretium quis lectus suspendisse potenti in eleifend quam a odio in","createdAt":"2022-04-04 07:49:46","updatedAt":"2022-05-10 15:43:00"},
{"id":3,"name":"Hyacinthie Redihough","description":"nonummy integer non velit donec diam neque vestibulum eget vulputate ut","createdAt":"2022-06-24 08:34:21","updatedAt":"2022-01-06 12:12:39"},
{"id":4,"name":"Kissie Snowman","description":"lacus at velit vivamus vel nulla eget eros elementum pellentesque quisque porta volutpat erat quisque erat eros viverra","createdAt":"2021-08-20 18:01:55","updatedAt":"2022-06-24 05:28:50"},
{"id":5,"name":"Stanton Scourge","description":"maecenas ut massa quis augue luctus tincidunt nulla mollis molestie lorem quisque","createdAt":"2021-07-14 08:20:52","updatedAt":"2022-03-03 09:22:20"},
{"id":6,"name":"Farra Leverentz","description":"non quam nec dui luctus rutrum nulla tellus in sagittis dui vel nisl duis ac nibh fusce lacus purus aliquet","createdAt":"2022-01-13 05:46:33","updatedAt":"2021-11-10 17:20:31"},
{"id":7,"name":"Linnie Eastham","description":"ipsum primis in faucibus orci luctus et ultrices posuere cubilia curae donec pharetra","createdAt":"2022-04-05 00:39:28","updatedAt":"2022-03-30 08:59:06"},
{"id":8,"name":"Morry Ielden","description":"lorem integer tincidunt ante vel ipsum praesent blandit lacinia erat vestibulum sed magna","createdAt":"2021-10-25 04:50:41","updatedAt":"2021-11-22 00:59:02"},
{"id":9,"name":"Briana Klesel","description":"at nulla suspendisse potenti cras in purus eu magna vulputate luctus cum sociis natoque penatibus et magnis dis","createdAt":"2022-01-29 19:53:52","updatedAt":"2022-05-26 05:39:47"},
{"id":10,"name":"Caprice Audenis","description":"at ipsum ac tellus semper interdum mauris ullamcorper purus sit amet nulla quisque","createdAt":"2022-06-25 15:38:53","updatedAt":"2022-03-02 03:42:40"},
{"id":11,"name":"Adelle Shayler","description":"aenean lectus pellentesque eget nunc donec quis orci eget orci","createdAt":"2021-10-27 09:11:25","updatedAt":"2022-03-31 18:26:58"},
{"id":12,"name":"Karim Scurr","description":"feugiat et eros vestibulum ac est lacinia nisi venenatis tristique fusce congue diam id ornare imperdiet","createdAt":"2021-10-18 13:51:11","updatedAt":"2022-02-06 13:06:33"},
{"id":13,"name":"Hollie Mahaffey","description":"ullamcorper augue a suscipit nulla elit ac nulla sed vel enim sit amet","createdAt":"2022-02-28 04:34:23","updatedAt":"2021-10-15 18:55:05"},
{"id":14,"name":"Andres Olenikov","description":"elementum pellentesque quisque porta volutpat erat quisque erat eros viverra eget congue eget semper rutrum nulla nunc","createdAt":"2022-05-06 08:51:40","updatedAt":"2022-02-28 22:52:39"},
{"id":15,"name":"Welch Warr","description":"odio in hac habitasse platea dictumst maecenas ut massa quis augue luctus tincidunt nulla mollis molestie lorem quisque ut","createdAt":"2021-11-01 04:46:45","updatedAt":"2022-05-06 07:24:09"},
{"id":16,"name":"Aigneis Bamber","description":"convallis nulla neque libero convallis eget eleifend luctus ultricies eu nibh quisque id justo sit amet sapien","createdAt":"2022-03-04 14:13:37","updatedAt":"2022-01-06 02:17:42"},
{"id":17,"name":"Tommi New","description":"quisque id justo sit amet sapien dignissim vestibulum vestibulum ante ipsum primis in faucibus orci luctus et ultrices posuere cubilia","createdAt":"2021-12-19 20:30:55","updatedAt":"2021-11-15 21:52:39"},
{"id":18,"name":"Dulsea Scargill","description":"donec ut dolor morbi vel lectus in quam fringilla rhoncus","createdAt":"2021-11-17 03:58:36","updatedAt":"2021-10-03 18:06:24"},
{"id":19,"name":"Evered Syddon","description":"vitae mattis nibh ligula nec sem duis aliquam convallis nunc proin at turpis a","createdAt":"2022-01-11 22:56:49","updatedAt":"2021-11-07 14:46:47"},
{"id":20,"name":"Tracie Catton","description":"quis tortor id nulla ultrices aliquet maecenas leo odio condimentum id luctus nec molestie sed justo","createdAt":"2021-12-21 09:56:23","updatedAt":"2022-02-03 04:00:02"}]